zope.publisher-7.2-py3.11-nspkg.pth
zope/publisher/__init__.py
zope/publisher/base.py
zope/publisher/browser.py
zope/publisher/configure.txt
zope/publisher/configure.zcml
zope/publisher/contenttype.py
zope/publisher/defaultview.py
zope/publisher/ftp.py
zope/publisher/http.py
zope/publisher/httpresults.txt
zope/publisher/meta.zcml
zope/publisher/normal.clb
zope/publisher/paste.py
zope/publisher/paste.txt
zope/publisher/principallogging.py
zope/publisher/publish.py
zope/publisher/skinnable.py
zope/publisher/skinnable.txt
zope/publisher/testing.py
zope/publisher/xmlrpc.py
zope/publisher/xmlrpc.txt
zope/publisher/zcml.py
zope/publisher/interfaces/__init__.py
zope/publisher/interfaces/browser.py
zope/publisher/interfaces/ftp.py
zope/publisher/interfaces/http.py
zope/publisher/interfaces/logginginfo.py
zope/publisher/interfaces/xmlrpc.py
zope/publisher/tests/__init__.py
zope/publisher/tests/basetestiapplicationrequest.py
zope/publisher/tests/basetestipublicationrequest.py
zope/publisher/tests/basetestipublisherrequest.py
zope/publisher/tests/publication.py
zope/publisher/tests/test_baserequest.py
zope/publisher/tests/test_baseresponse.py
zope/publisher/tests/test_browser.py
zope/publisher/tests/test_browserlanguages.py
zope/publisher/tests/test_browserrequest.py
zope/publisher/tests/test_browserresponse.py
zope/publisher/tests/test_defaultview.py
zope/publisher/tests/test_ftp.py
zope/publisher/tests/test_http.py
zope/publisher/tests/test_httpcharsets.py
zope/publisher/tests/test_ipublication.py
zope/publisher/tests/test_mapply.py
zope/publisher/tests/test_paste.py
zope/publisher/tests/test_principallogging.py
zope/publisher/tests/test_publisher.py
zope/publisher/tests/test_requestdataproperty.py
zope/publisher/tests/test_skinnable.py
zope/publisher/tests/test_testing.py
zope/publisher/tests/test_xmlrpc.py
zope/publisher/tests/test_xmlrpcrequest.py
zope/publisher/tests/test_zcml.py
zope/publisher/tests/views.py
zope/publisher/tests/xmlrpcviews.py
zope.publisher-7.2.dist-info/LICENSE.txt
zope.publisher-7.2.dist-info/METADATA
zope.publisher-7.2.dist-info/WHEEL
zope.publisher-7.2.dist-info/entry_points.txt
zope.publisher-7.2.dist-info/namespace_packages.txt
zope.publisher-7.2.dist-info/top_level.txt
zope.publisher-7.2.dist-info/RECORD
