Metadata-Version: 2.1
Name: zope.publisher
Version: 7.2
Summary: The Zope publisher publishes Python objects on the web.
Home-page: https://github.com/zopefoundation/zope.publisher
Author: Zope Foundation and Contributors
Author-email: zope-dev@zope.dev
License: ZPL 2.1
Classifier: Development Status :: 5 - Production/Stable
Classifier: Intended Audience :: Developers
Classifier: License :: OSI Approved :: Zope Public License
Classifier: Programming Language :: Python
Classifier: Programming Language :: Python :: 3
Classifier: Programming Language :: Python :: 3.9
Classifier: Programming Language :: Python :: 3.10
Classifier: Programming Language :: Python :: 3.11
Classifier: Programming Language :: Python :: 3.12
Classifier: Programming Language :: Python :: 3.13
Classifier: Programming Language :: Python :: Implementation :: CPython
Classifier: Programming Language :: Python :: Implementation :: PyPy
Classifier: Natural Language :: English
Classifier: Operating System :: OS Independent
Classifier: Topic :: Internet :: WWW/HTTP
Requires-Python: >=3.9
License-File: LICENSE.txt
Requires-Dist: multipart>=1.1.0
Requires-Dist: setuptools
Requires-Dist: zope.browser
Requires-Dist: zope.component
Requires-Dist: zope.configuration
Requires-Dist: zope.contenttype>=4.0.0
Requires-Dist: zope.event
Requires-Dist: zope.exceptions
Requires-Dist: zope.i18n>=4.0.0
Requires-Dist: zope.interface>=4.0.1
Requires-Dist: zope.location
Requires-Dist: zope.proxy
Requires-Dist: zope.security>=4.0.0
Provides-Extra: test
Requires-Dist: zope.testing; extra == "test"
Requires-Dist: zope.testrunner; extra == "test"
Provides-Extra: docs
Requires-Dist: Sphinx; extra == "docs"
Requires-Dist: repoze.sphinx.autointerface; extra == "docs"
Requires-Dist: sphinx_rtd_theme; extra == "docs"
